dmenuplaylist/__init__.py
dmenuplaylist/__main__.py
dmenuplaylist/config.py
dmenuplaylist/initial_setup.py
dmenuplaylist/options.py
dmenuplaylist/prompts.py
dmenuplaylist/system.py
dmenuplaylist/utils.py
dmenuplaylist-0.0.0b5.dist-info/LICENSE
dmenuplaylist-0.0.0b5.dist-info/METADATA
dmenuplaylist-0.0.0b5.dist-info/WHEEL
dmenuplaylist-0.0.0b5.dist-info/entry_points.txt
dmenuplaylist-0.0.0b5.dist-info/top_level.txt
dmenuplaylist-0.0.0b5.dist-info/RECORD
