Metadata-Version: 2.1
Name: dmenuplaylist
Version: 0.0.0b5
Summary: Simple playlist manager, meant to be used with mpv.
License: GNU General Public License v3 (GPLv3)
Project-URL: repository, https://codeberg.org/johndovern/dmenuplaylist
Keywords: mpv,dmenu
License-File: LICENSE
Requires-Dist: loadconf
Requires-Dist: promptx (>=0.0.5)
